{
  "date": "2026-07-02",
  "prev_date": "2026-07-01",
  "periods": {
    "7": {
      "period": "近 7 日",
      "source": "ai",
      "summary": "近7日全站无综合赛道热点，具体分类新增在读11.4万、增长作品21本，新书题材以系统（4本）和反派（2本）为主，重生、幼崽、修仙各1本。编辑判断：系统类新书集中涌现，但整体数据量不足，尚未形成全站级热点。",
      "fallback_summary": "近 7 日暂无足够数据判断全站热点。",
      "hot_genres": [],
      "hot_types": [
        {
          "name": "",
          "score": 114000,
          "new_count": 15,
          "dropped_count": 15,
          "read_count": 21,
          "read_growth_total": 114000.0,
          "active_days": 7
        }
      ],
      "hot_themes": [
        {
          "name": "系统",
          "count": 4,
          "category_count": 1
        },
        {
          "name": "反派",
          "count": 2,
          "category_count": 1
        },
        {
          "name": "重生",
          "count": 1,
          "category_count": 1
        },
        {
          "name": "幼崽",
          "count": 1,
          "category_count": 1
        },
        {
          "name": "修仙",
          "count": 1,
          "category_count": 1
        }
      ]
    },
    "14": {
      "period": "近 14 日",
      "source": "ai",
      "summary": "近14日全站无综合赛道热点，具体分类新增在读42.8万、增长作品39本，新书题材系统（7本）领跑，反派、远古各2本，重生、幼崽、修仙各1本。编辑判断：系统题材持续扩容，远古元素初现，但阅读增长分散，未达全站热点阈值。",
      "fallback_summary": "近 14 日暂无足够数据判断全站热点。",
      "hot_genres": [],
      "hot_types": [
        {
          "name": "",
          "score": 428000,
          "new_count": 28,
          "dropped_count": 28,
          "read_count": 39,
          "read_growth_total": 428000.0,
          "active_days": 14
        }
      ],
      "hot_themes": [
        {
          "name": "系统",
          "count": 7,
          "category_count": 1
        },
        {
          "name": "反派",
          "count": 2,
          "category_count": 1
        },
        {
          "name": "远古",
          "count": 2,
          "category_count": 1
        },
        {
          "name": "重生",
          "count": 1,
          "category_count": 1
        },
        {
          "name": "幼崽",
          "count": 1,
          "category_count": 1
        },
        {
          "name": "修仙",
          "count": 1,
          "category_count": 1
        }
      ]
    },
    "30": {
      "period": "近 30 日",
      "source": "ai",
      "summary": "近30日全站无综合赛道热点，具体分类新增在读42.8万、增长作品39本，新书题材系统（7本）主导，反派、远古各2本，重生、幼崽、修仙各1本。编辑判断：系统类新书数量稳定，但阅读增长与作品数匹配度低，全站热点尚未成型。",
      "fallback_summary": "近 30 日暂无足够数据判断全站热点。",
      "hot_genres": [],
      "hot_types": [
        {
          "name": "",
          "score": 428000,
          "new_count": 48,
          "dropped_count": 28,
          "read_count": 39,
          "read_growth_total": 428000.0,
          "active_days": 15
        }
      ],
      "hot_themes": [
        {
          "name": "系统",
          "count": 7,
          "category_count": 1
        },
        {
          "name": "反派",
          "count": 2,
          "category_count": 1
        },
        {
          "name": "远古",
          "count": 2,
          "category_count": 1
        },
        {
          "name": "重生",
          "count": 1,
          "category_count": 1
        },
        {
          "name": "幼崽",
          "count": 1,
          "category_count": 1
        },
        {
          "name": "修仙",
          "count": 1,
          "category_count": 1
        }
      ]
    },
    "all": {
      "period": "全部样本",
      "source": "ai",
      "summary": "全部样本无综合赛道热点，具体分类新增在读42.8万、增长作品39本，新书题材系统（7本）最突出，反派、远古各2本，重生、幼崽、修仙各1本。编辑判断：系统题材为近期新书主力，但全站阅读增长动能不足，暂无明确热点方向。",
      "fallback_summary": "全部样本暂无足够数据判断全站热点。",
      "hot_genres": [],
      "hot_types": [
        {
          "name": "",
          "score": 428000,
          "new_count": 48,
          "dropped_count": 28,
          "read_count": 39,
          "read_growth_total": 428000.0,
          "active_days": 15
        }
      ],
      "hot_themes": [
        {
          "name": "系统",
          "count": 7,
          "category_count": 1
        },
        {
          "name": "反派",
          "count": 2,
          "category_count": 1
        },
        {
          "name": "远古",
          "count": 2,
          "category_count": 1
        },
        {
          "name": "重生",
          "count": 1,
          "category_count": 1
        },
        {
          "name": "幼崽",
          "count": 1,
          "category_count": 1
        },
        {
          "name": "修仙",
          "count": 1,
          "category_count": 1
        }
      ]
    }
  }
}